worldai_processing/__init__.py
worldai_processing-0.1.0.dist-info/METADATA
worldai_processing-0.1.0.dist-info/WHEEL
worldai_processing-0.1.0.dist-info/top_level.txt
worldai_processing-0.1.0.dist-info/RECORD
