Metadata-Version: 2.4
Name: worldai-processing
Version: 0.1.0
Summary: Processing utilities for WorldAI
Author-email: WorldAI <info@example.com>
License-Expression: MIT
Keywords: worldai,processing
Requires-Python: >=3.8
Requires-Dist: worldai>=0.1.0
